odoo8_addon_account_journal_always_check_date-8.0.0.1.0.99.dev8-py2.7-nspkg.pth
odoo8_addon_account_journal_always_check_date-8.0.0.1.0.99.dev8.dist-info/METADATA
odoo8_addon_account_journal_always_check_date-8.0.0.1.0.99.dev8.dist-info/RECORD
odoo8_addon_account_journal_always_check_date-8.0.0.1.0.99.dev8.dist-info/WHEEL
odoo8_addon_account_journal_always_check_date-8.0.0.1.0.99.dev8.dist-info/namespace_packages.txt
odoo8_addon_account_journal_always_check_date-8.0.0.1.0.99.dev8.dist-info/top_level.txt
odoo_addons/account_journal_always_check_date/__init__.py
odoo_addons/account_journal_always_check_date/__openerp__.py
odoo_addons/account_journal_always_check_date/account_journal.py
odoo_addons/account_journal_always_check_date/i18n/account_journal_always_check_date.pot
odoo_addons/account_journal_always_check_date/i18n/ar.po
odoo_addons/account_journal_always_check_date/i18n/bs.po
odoo_addons/account_journal_always_check_date/i18n/ca.po
odoo_addons/account_journal_always_check_date/i18n/ca_ES.po
odoo_addons/account_journal_always_check_date/i18n/cs.po
odoo_addons/account_journal_always_check_date/i18n/da.po
odoo_addons/account_journal_always_check_date/i18n/de.po
odoo_addons/account_journal_always_check_date/i18n/en_GB.po
odoo_addons/account_journal_always_check_date/i18n/es.po
odoo_addons/account_journal_always_check_date/i18n/es_CR.po
odoo_addons/account_journal_always_check_date/i18n/es_EC.po
odoo_addons/account_journal_always_check_date/i18n/es_ES.po
odoo_addons/account_journal_always_check_date/i18n/es_MX.po
odoo_addons/account_journal_always_check_date/i18n/es_VE.po
odoo_addons/account_journal_always_check_date/i18n/et.po
odoo_addons/account_journal_always_check_date/i18n/fi.po
odoo_addons/account_journal_always_check_date/i18n/fr.po
odoo_addons/account_journal_always_check_date/i18n/gl.po
odoo_addons/account_journal_always_check_date/i18n/hr.po
odoo_addons/account_journal_always_check_date/i18n/hr_HR.po
odoo_addons/account_journal_always_check_date/i18n/hu.po
odoo_addons/account_journal_always_check_date/i18n/id.po
odoo_addons/account_journal_always_check_date/i18n/it.po
odoo_addons/account_journal_always_check_date/i18n/ja.po
odoo_addons/account_journal_always_check_date/i18n/lt.po
odoo_addons/account_journal_always_check_date/i18n/lt_LT.po
odoo_addons/account_journal_always_check_date/i18n/mk.po
